gql_relay_result/__init__.py
gql_relay_result/relay_result.py
gql_relay_result-0.0.6.dist-info/LICENSE
gql_relay_result-0.0.6.dist-info/METADATA
gql_relay_result-0.0.6.dist-info/WHEEL
gql_relay_result-0.0.6.dist-info/top_level.txt
gql_relay_result-0.0.6.dist-info/RECORD
