Metadata-Version: 2.1
Name: gql-relay-result
Version: 0.0.6
Summary: Pageable resultset for gql queries
Home-page: https://github.com/universalappfactory/gql-relay-result
Author: UniversalAppfactory
Author-email: info@universalappfactory.de
License: UNKNOWN
Keywords: api graphql protocol rest relay gql client
Platform: UNKNOWN
Classifier: Programming Language :: Python :: 3
Classifier: License :: OSI Approved :: MIT License
Classifier: Operating System :: OS Independent
Requires-Python: >=3.6
Requires-Dist: gql (>=3.0.0a4)
